<?xml version="1.0" encoding="UTF-8"?>
<objects serializationModel="Studio.02.03.00">
	<object class="AudioFile" id="{00a7d00e-93c1-446a-97a5-600c95f47155}">
		<property name="assetPath">
			<value>SFXPackages/RAREVGSFX 2/XBOX/MEGA MAN 10 (360)/MM10 SFX/SE [109].wav</value>
		</property>
		<property name="frequencyInKHz">
			<value>44.1489983</value>
		</property>
		<property name="channelCount">
			<value>1</value>
		</property>
		<property name="length">
			<value>0.82339350834673497</value>
		</property>
		<relationship name="masterAssetFolder">
			<destination>{ce90175b-3282-4b57-a88a-a86b80b7815a}</destination>
		</relationship>
	</object>
</objects>
