<?xml version="1.0" encoding="UTF-8"?>
<objects serializationModel="Studio.02.03.00">
	<object class="AudioFile" id="{2731a1d9-82f9-4471-9a09-87d8d3f7f436}">
		<property name="assetPath">
			<value>SFXPackages/RAREVGSFX/PLAYSTATION/METAL SLUG 3D (PS2)/Sounds/all_00191.wav</value>
		</property>
		<property name="frequencyInKHz">
			<value>22.0499992</value>
		</property>
		<property name="channelCount">
			<value>1</value>
		</property>
		<property name="length">
			<value>0.5701587301587302</value>
		</property>
		<relationship name="masterAssetFolder">
			<destination>{ce90175b-3282-4b57-a88a-a86b80b7815a}</destination>
		</relationship>
	</object>
</objects>
