<?xml version="1.0" encoding="UTF-8"?>
<objects serializationModel="Studio.02.03.00">
	<object class="AudioFile" id="{47f3587d-c54f-4e78-af7d-ad6fbf5991ab}">
		<property name="assetPath">
			<value>SFXPackages/RAREVGSFX/PLAYSTATION/R&amp;C UP YOUR ARSENAL (PS2)/ratchet_and_clank_up_your_arsenal_ps2.iso_13168.wav</value>
		</property>
		<property name="frequencyInKHz">
			<value>22.0499992</value>
		</property>
		<property name="channelCount">
			<value>1</value>
		</property>
		<property name="length">
			<value>0.45968253968253969</value>
		</property>
		<relationship name="masterAssetFolder">
			<destination>{ce90175b-3282-4b57-a88a-a86b80b7815a}</destination>
		</relationship>
	</object>
</objects>
