<?xml version="1.0" encoding="UTF-8"?>
<objects serializationModel="Studio.02.03.00">
	<object class="AudioFile" id="{48f7fa8b-8d52-4872-8913-e44ac5b29604}">
		<property name="assetPath">
			<value>SFXPackages/RAREVGSFX/PLAYSTATION/CRASH BANDICOOT WRATH OF CORTEX (PS2)/Sound Effects/uw_tube.wav</value>
		</property>
		<property name="frequencyInKHz">
			<value>22.0499992</value>
		</property>
		<property name="channelCount">
			<value>1</value>
		</property>
		<property name="length">
			<value>4.4524263038548755</value>
		</property>
		<relationship name="masterAssetFolder">
			<destination>{ce90175b-3282-4b57-a88a-a86b80b7815a}</destination>
		</relationship>
	</object>
</objects>
