<?xml version="1.0" encoding="UTF-8"?>
<objects serializationModel="Studio.02.03.00">
	<object class="AudioFile" id="{70830411-3d3c-4bf5-9304-3b6d12b5af70}">
		<property name="assetPath">
			<value>SFXPackages/RAREVGSFX/PLAYSTATION/R&amp;C UP YOUR ARSENAL (PS2)/ratchet_and_clank_up_your_arsenal_ps2.iso_03391.wav</value>
		</property>
		<property name="frequencyInKHz">
			<value>22.0499992</value>
		</property>
		<property name="channelCount">
			<value>1</value>
		</property>
		<property name="length">
			<value>0.43174603174603177</value>
		</property>
		<relationship name="masterAssetFolder">
			<destination>{ce90175b-3282-4b57-a88a-a86b80b7815a}</destination>
		</relationship>
	</object>
</objects>
