<?xml version="1.0" encoding="UTF-8"?>
<objects serializationModel="Studio.02.03.00">
	<object class="AudioFile" id="{8e9f69c1-d665-4397-9a33-03ee8d7e7b77}">
		<property name="assetPath">
			<value>SFXPackages/RAREVGSFX 2/XBOX/ROLLERCOASTER TYCOON (XBOX)/RCT SFX/open_stats.wav</value>
		</property>
		<property name="frequencyInKHz">
			<value>22.0499992</value>
		</property>
		<property name="channelCount">
			<value>1</value>
		</property>
		<property name="length">
			<value>0.18566893424036282</value>
		</property>
		<relationship name="masterAssetFolder">
			<destination>{ce90175b-3282-4b57-a88a-a86b80b7815a}</destination>
		</relationship>
	</object>
</objects>
