<?xml version="1.0" encoding="UTF-8"?>
<objects serializationModel="Studio.02.03.00">
	<object class="AudioFile" id="{95c15e51-407f-4796-8fc6-771b87eac0d7}">
		<property name="assetPath">
			<value>SFXPackages/RAREVGSFX 2/PLAYSTATION/TOMB RAIDER CHRONICLES (PS1)/GAMEWAD_01294.wav</value>
		</property>
		<property name="frequencyInKHz">
			<value>11.0249996</value>
		</property>
		<property name="channelCount">
			<value>1</value>
		</property>
		<property name="length">
			<value>0.62222222222222223</value>
		</property>
		<relationship name="masterAssetFolder">
			<destination>{ce90175b-3282-4b57-a88a-a86b80b7815a}</destination>
		</relationship>
	</object>
</objects>
