<?xml version="1.0" encoding="UTF-8"?>
<objects serializationModel="Studio.02.03.00">
	<object class="AudioFile" id="{9c5e4a5f-1971-4311-ab0f-cb2944a107ac}">
		<property name="assetPath">
			<value>SFXPackages/RAREVGSFX 2/PLAYSTATION/BRAVE WARS (PS2)/Shinseiki_Yuusha_Taisen_00413.wav</value>
		</property>
		<property name="frequencyInKHz">
			<value>22.0499992</value>
		</property>
		<property name="channelCount">
			<value>1</value>
		</property>
		<property name="length">
			<value>2.3923809523809525</value>
		</property>
		<relationship name="masterAssetFolder">
			<destination>{ce90175b-3282-4b57-a88a-a86b80b7815a}</destination>
		</relationship>
	</object>
</objects>
