<?xml version="1.0" encoding="UTF-8"?>
<objects serializationModel="Studio.02.03.00">
	<object class="AudioFile" id="{b484c20a-4434-415c-8d16-8addc1b0f9a8}">
		<property name="assetPath">
			<value>SFXPackages/RAREVGSFX 2/PLAYSTATION/HERCULES (PS1)/Sound Effects/Hercules/SN7_00018.wav</value>
		</property>
		<property name="frequencyInKHz">
			<value>8</value>
		</property>
		<property name="channelCount">
			<value>1</value>
		</property>
		<property name="length">
			<value>1.113</value>
		</property>
		<relationship name="masterAssetFolder">
			<destination>{ce90175b-3282-4b57-a88a-a86b80b7815a}</destination>
		</relationship>
	</object>
</objects>
