<?xml version="1.0" encoding="UTF-8"?>
<objects serializationModel="Studio.02.03.00">
	<object class="AudioFile" id="{d67fc6bb-d0d8-4ff9-ad46-0dd9555179e0}">
		<property name="assetPath">
			<value>SFXPackages/RAREVGSFX/PLAYSTATION/METAL SLUG 3D (PS2)/Sounds/all_00346.wav</value>
		</property>
		<property name="frequencyInKHz">
			<value>24</value>
		</property>
		<property name="channelCount">
			<value>1</value>
		</property>
		<property name="length">
			<value>4.4493333333333336</value>
		</property>
		<relationship name="masterAssetFolder">
			<destination>{ce90175b-3282-4b57-a88a-a86b80b7815a}</destination>
		</relationship>
	</object>
</objects>
