<?xml version="1.0" encoding="UTF-8"?>
<objects serializationModel="Studio.02.03.00">
	<object class="AudioFile" id="{e6884ea0-6b95-4686-a826-496f723ac4ac}">
		<property name="assetPath">
			<value>SFXPackages/RAREVGSFX 2/XBOX/DIDDY KONG RACING (XBOX)/Characters/Xbox - Diddy Kong Racing Adventure - Characters/Character#6.wav</value>
		</property>
		<property name="frequencyInKHz">
			<value>44.0999985</value>
		</property>
		<property name="channelCount">
			<value>1</value>
		</property>
		<property name="length">
			<value>0.30752834467120183</value>
		</property>
		<relationship name="masterAssetFolder">
			<destination>{ce90175b-3282-4b57-a88a-a86b80b7815a}</destination>
		</relationship>
	</object>
</objects>
