<?xml version="1.0" encoding="UTF-8"?>
<objects serializationModel="Studio.02.03.00">
	<object class="AudioFile" id="{ec8d3900-d255-4b4b-9da9-3d8bb9a95575}">
		<property name="assetPath">
			<value>SFXPackages/RAREVGSFX 2/NINTENDO/WARIO LAND III (GBC)/Warioland Super Mario Land 3/Bounce.wav</value>
		</property>
		<property name="frequencyInKHz">
			<value>22.0499992</value>
		</property>
		<property name="channelCount">
			<value>1</value>
		</property>
		<property name="length">
			<value>0.82503401360544215</value>
		</property>
		<relationship name="masterAssetFolder">
			<destination>{ce90175b-3282-4b57-a88a-a86b80b7815a}</destination>
		</relationship>
	</object>
</objects>
