<?xml version="1.0" encoding="UTF-8"?>
<objects serializationModel="Studio.02.03.00">
	<object class="AudioFile" id="{f18d43f0-8abf-4d96-b2c4-7c9da16d2074}">
		<property name="assetPath">
			<value>SFXPackages/RAREVGSFX/PLAYSTATION/CRASH BANDICOOT WRATH OF CORTEX (PS2)/Sound Effects/cnv_blt.wav</value>
		</property>
		<property name="frequencyInKHz">
			<value>22.0499992</value>
		</property>
		<property name="channelCount">
			<value>1</value>
		</property>
		<property name="length">
			<value>6.4841723356009071</value>
		</property>
		<relationship name="masterAssetFolder">
			<destination>{ce90175b-3282-4b57-a88a-a86b80b7815a}</destination>
		</relationship>
	</object>
</objects>
