<?xml version="1.0" encoding="UTF-8"?>
<objects serializationModel="Studio.02.03.00">
	<object class="AudioFile" id="{f957d377-cb5b-4a10-a83a-4b759ada21ca}">
		<property name="assetPath">
			<value>SFXPackages/RAREVGSFX/PLAYSTATION/PARTY GIRLS (PS2)/Kana Momozono/CHR_6_11.HBS_00006.wav</value>
		</property>
		<property name="frequencyInKHz">
			<value>22.0499992</value>
		</property>
		<property name="channelCount">
			<value>1</value>
		</property>
		<property name="length">
			<value>1.0323809523809524</value>
		</property>
		<relationship name="masterAssetFolder">
			<destination>{ce90175b-3282-4b57-a88a-a86b80b7815a}</destination>
		</relationship>
	</object>
</objects>
